setup.py
txDiscourse/__init__.py
txDiscourse/client.py
txDiscourse/example.py
txDiscourse/test_api_calls.py
txDiscourse.egg-info/PKG-INFO
txDiscourse.egg-info/SOURCES.txt
txDiscourse.egg-info/dependency_links.txt
txDiscourse.egg-info/requires.txt
txDiscourse.egg-info/top_level.txt