Metadata-Version: 1.1
Name: txDiscourse
Version: 0.1.2
Summary: Discourse API wrapper for Twisted
Home-page: https://github.com/theGeoffrey/txDiscourse
Author: Anouk Ruhaak
Author-email: UNKNOWN
License: APL2
Download-URL: https://pypi.python.org/packages/2.7/t/txDiscourse/txDiscourse-0.1.2-py2.7.egg
Platform: UNKNOWN
Classifier: Programming Language :: Python :: 2.7
Classifier: Framework :: Twisted
